Metadata-Version: 2.1
Name: cachedcomplete-updated
Version: 0.1.0
Summary: Cached wrapper for python argcomplete
Home-page: https://github.com/reef-technologies/cachedcomplete
Author: 
Author-email: 
License: MIT License
Project-URL: Source Code, https://github.com/reef-technologies/cachedcomplete
Platform: MacOS X
Platform: Posix
Classifier: Environment :: Console
Classifier: Intended Audience :: Developers
Classifier: License :: OSI Approved :: MIT License
Classifier: Operating System :: MacOS :: MacOS X
Classifier: Operating System :: POSIX
Classifier: Programming Language :: Python
Classifier: Programming Language :: Python :: 3
Classifier: Programming Language :: Python :: 3.8
Classifier: Programming Language :: Python :: 3.9
Classifier: Programming Language :: Python :: 3.10
Classifier: Programming Language :: Python :: 3.11
Classifier: Programming Language :: Python :: 3.12
Classifier: Programming Language :: Python :: Implementation :: CPython
Classifier: Development Status :: 4 - Beta
Classifier: Topic :: Software Development
Classifier: Topic :: Software Development :: Libraries :: Python Modules
Classifier: Topic :: System :: Shells
Classifier: Topic :: Terminals
License-File: LICENSE
Requires-Dist: argcomplete<4,>=3.1.6
